{
  "sections": {
    "banner": {
      "type": "collection-banner",
      "settings": {
        "full_width": false,
        "allow_transparent_header": false,
        "enable_parallax": false,
        "show_collection_title": true,
        "show_collection_description": true,
        "show_collection_image": false,
        "collection_title_size": "h0",
        "image_size": "sm",
        "mobile_text_position": "place-self-center text-center",
        "desktop_text_position": "sm:place-self-center sm:text-center",
        "featured_product": "125209-little-dutch-kids-sunglasses-sailors-bay-round",
        "featured_product_heading": "Featured product",
        "text_color": "#ffffff",
        "overlay_color": "#1d2f50",
        "overlay_opacity": 30
      }
    },
    "2daa9e15-8fa8-4c7d-ab51-fb4367f91968": {
      "type": "hot-spots",
      "blocks": {
        "template--16669196746994__2daa9e15-8fa8-4c7d-ab51-fb4367f91968-167948156385ba0adc-0": {
          "type": "item",
          "settings": {
            "horizontal_position": 16,
            "vertical_position": 59,
            "horizontal_position_mobile": 24,
            "vertical_position_mobile": 70,
            "icon_width": 32,
            "title": "Really nice sofa",
            "content": "<p>Share useful information about your product features.<\/p><p> <a href=\"\/products\/ld-chair-pink\" title=\"LD4950 - LD Chair - pink - (1)\">View Product<\/a><\/p>"
          }
        },
        "template--16669196746994__2daa9e15-8fa8-4c7d-ab51-fb4367f91968-167948156385ba0adc-1": {
          "type": "item",
          "settings": {
            "horizontal_position": 74,
            "vertical_position": 14,
            "horizontal_position_mobile": 62,
            "vertical_position_mobile": 14,
            "icon_width": 32,
            "title": "Really nice Lampshade",
            "content": "<p>Share useful information about your product features.<\/p><p><a href=\"\/products\/120525-little-dutch-paint-book\" title=\"120525 - Little Dutch Paint Book\">View Product<\/a><\/p>"
          }
        },
        "template--16669196746994__2daa9e15-8fa8-4c7d-ab51-fb4367f91968-167948156385ba0adc-2": {
          "type": "item",
          "settings": {
            "horizontal_position": 64,
            "vertical_position": 75,
            "horizontal_position_mobile": 83,
            "vertical_position_mobile": 75,
            "icon_width": 32,
            "title": "Really Nice Table",
            "content": "<p>Share useful information about your product features.<\/p><p><a href=\"\/products\/125100-little-dutch-beach-towel-sailors-bay\" title=\"125100 Little Dutch Beach Towel Sailors Bay\">View Product<\/a><\/p>"
          }
        }
      },
      "block_order": [
        "template--16669196746994__2daa9e15-8fa8-4c7d-ab51-fb4367f91968-167948156385ba0adc-0",
        "template--16669196746994__2daa9e15-8fa8-4c7d-ab51-fb4367f91968-167948156385ba0adc-1",
        "template--16669196746994__2daa9e15-8fa8-4c7d-ab51-fb4367f91968-167948156385ba0adc-2"
      ],
      "settings": {
        "full_width": true,
        "image": "shopify:\/\/shop_images\/Bathroom_835d5baf-29d5-45d8-b564-efbcfbcb04d8.jpg",
        "mobile_image": "shopify:\/\/shop_images\/Bathroom.jpg",
        "title": "",
        "content": "",
        "button_text": "",
        "button_url": "",
        "desktop_text_position": "place-self-start text-start",
        "image_background": "",
        "image_background_gradient": "",
        "overlay_color": "#000000",
        "overlay_opacity": 0,
        "overlay_text_color": "#ffffff",
        "overlay_button_background": "",
        "overlay_button_text_color": "",
        "hot_spot_dot_background": "#ffffff",
        "hot_spot_dot_text_color": "#000000",
        "hot_spot_content_background": "#ffffff",
        "hot_spot_content_text_color": "#000000",
        "hot_spot_content_opacity": 90,
        "hot_spot_content_blur_radius": 3
      }
    },
    "main": {
      "type": "main-collection",
      "settings": {
        "products_per_page": 50,
        "products_per_row_mobile": "2",
        "products_per_row_desktop": 4,
        "filter_layout": "sidebar",
        "show_sort_by": true,
        "show_filters": true,
        "show_filter_group_name": false,
        "show_color_swatch": true,
        "show_empty_filter_values": false,
        "show_filter_values_count": true,
        "open_first_filter_group": false
      }
    }
  },
  "order": [
    "banner",
    "2daa9e15-8fa8-4c7d-ab51-fb4367f91968",
    "main"
  ]
}
